{
  "mavericks": {
    "Sterling Brown": {
      "id": 1628425,
      "playing_state": "active",
      "GROUP_SET": "Last 10 Games",
      "GROUP_VALUE": "2021-22",
      "GP": 10,
      "W": 9,
      "L": 1,
      "W_PCT": 0.9,
      "MIN": 116.28833333333333,
      "FGM": 12,
      "FGA": 29,
      "FG_PCT": 0.414,
      "FG3M": 5,
      "FG3A": 16,
      "FG3_PCT": 0.313,
      "FTM": 6,
      "FTA": 7,
      "FT_PCT": 0.857,
      "OREB": 3,
      "DREB": 26,
      "REB": 29,
      "AST": 5,
      "TOV": 3,
      "STL": 1,
      "BLK": 2,
      "BLKA": 1,
      "PF": 9,
      "PFD": 4,
      "PTS": 35,
      "PLUS_MINUS": 32,
      "NBA_FANTASY_PTS": 83.3,
      "DD2": 0,
      "TD3": 0,
      "GP_RANK": 1,
      "W_RANK": 1,
      "L_RANK": 1,
      "W_PCT_RANK": 1,
      "MIN_RANK": 1,
      "FGM_RANK": 1,
      "FGA_RANK": 1,
      "FG_PCT_RANK": 1,
      "FG3M_RANK": 1,
      "FG3A_RANK": 1,
      "FG3_PCT_RANK": 1,
      "FTM_RANK": 1,
      "FTA_RANK": 1,
      "FT_PCT_RANK": 1,
      "OREB_RANK": 1,
      "DREB_RANK": 1,
      "REB_RANK": 1,
      "AST_RANK": 1,
      "TOV_RANK": 1,
      "STL_RANK": 1,
      "BLK_RANK": 1,
      "BLKA_RANK": 1,
      "PF_RANK": 1,
      "PFD_RANK": 1,
      "PTS_RANK": 1,
      "PLUS_MINUS_RANK": 1,
      "NBA_FANTASY_PTS_RANK": 1,
      "DD2_RANK": 1,
      "TD3_RANK": 1,
      "CFID": 36,
      "CFPARAMS": "2021-22"
    },
    "Trey Burke": {
      "id": 203504,
      "playing_state": "active",
      "GROUP_SET": "Last 10 Games",
      "GROUP_VALUE": "2021-22",
      "GP": 10,
      "W": 7,
      "L": 3,
      "W_PCT": 0.7,
      "MIN": 140.57,
      "FGM": 28,
      "FGA": 75,
      "FG_PCT": 0.373,
      "FG3M": 9,
      "FG3A": 33,
      "FG3_PCT": 0.273,
      "FTM": 6,
      "FTA": 6,
      "FT_PCT": 1.0,
      "OREB": 2,
      "DREB": 12,
      "REB": 14,
      "AST": 25,
      "TOV": 5,
      "STL": 4,
      "BLK": 0,
      "BLKA": 4,
      "PF": 16,
      "PFD": 7,
      "PTS": 71,
      "PLUS_MINUS": 9,
      "NBA_FANTASY_PTS": 132.3,
      "DD2": 0,
      "TD3": 0,
      "GP_RANK": 1,
      "W_RANK": 1,
      "L_RANK": 1,
      "W_PCT_RANK": 1,
      "MIN_RANK": 1,
      "FGM_RANK": 1,
      "FGA_RANK": 1,
      "FG_PCT_RANK": 1,
      "FG3M_RANK": 1,
      "FG3A_RANK": 1,
      "FG3_PCT_RANK": 1,
      "FTM_RANK": 1,
      "FTA_RANK": 1,
      "FT_PCT_RANK": 1,
      "OREB_RANK": 1,
      "DREB_RANK": 1,
      "REB_RANK": 1,
      "AST_RANK": 1,
      "TOV_RANK": 1,
      "STL_RANK": 1,
      "BLK_RANK": 1,
      "BLKA_RANK": 1,
      "PF_RANK": 1,
      "PFD_RANK": 1,
      "PTS_RANK": 1,
      "PLUS_MINUS_RANK": 1,
      "NBA_FANTASY_PTS_RANK": 1,
      "DD2_RANK": 1,
      "TD3_RANK": 1,
      "CFID": 36,
      "CFPARAMS": "2021-22"
    },
    "Marquese Chriss": {
      "id": 1627737,
      "playing_state": "active",
      "GROUP_SET": "Last 10 Games",
      "GROUP_VALUE": "2021-22",
      "GP": 10,
      "W": 9,
      "L": 1,
      "W_PCT": 0.9,
      "MIN": 107.35,
      "FGM": 24,
      "FGA": 37,
      "FG_PCT": 0.649,
      "FG3M": 6,
      "FG3A": 10,
      "FG3_PCT": 0.6,
      "FTM": 7,
      "FTA": 12,
      "FT_PCT": 0.583,
      "OREB": 5,
      "DREB": 25,
      "REB": 30,
      "AST": 4,
      "TOV": 6,
      "STL": 0,
      "BLK": 2,
      "BLKA": 3,
      "PF": 19,
      "PFD": 8,
      "PTS": 61,
      "PLUS_MINUS": 18,
      "NBA_FANTASY_PTS": 103.0,
      "DD2": 0,
      "TD3": 0,
      "GP_RANK": 1,
      "W_RANK": 1,
      "L_RANK": 1,
      "W_PCT_RANK": 1,
      "MIN_RANK": 1,
      "FGM_RANK": 1,
      "FGA_RANK": 1,
      "FG_PCT_RANK": 1,
      "FG3M_RANK": 1,
      "FG3A_RANK": 1,
      "FG3_PCT_RANK": 1,
      "FTM_RANK": 1,
      "FTA_RANK": 1,
      "FT_PCT_RANK": 1,
      "OREB_RANK": 1,
      "DREB_RANK": 1,
      "REB_RANK": 1,
      "AST_RANK": 1,
      "TOV_RANK": 1,
      "STL_RANK": 1,
      "BLK_RANK": 1,
      "BLKA_RANK": 1,
      "PF_RANK": 1,
      "PFD_RANK": 1,
      "PTS_RANK": 1,
      "PLUS_MINUS_RANK": 1,
      "NBA_FANTASY_PTS_RANK": 1,
      "DD2_RANK": 1,
      "TD3_RANK": 1,
      "CFID": 36,
      "CFPARAMS": "2021-22"
    },
    "Kristaps Porzingis": {
      "id": 204001,
      "playing_state": "active",
      "GROUP_SET": "Last 10 Games",
      "GROUP_VALUE": "2021-22",
      "GP": 10,
      "W": 5,
      "L": 5,
      "W_PCT": 0.5,
      "MIN": 317.07666666666665,
      "FGM": 68,
      "FGA": 146,
      "FG_PCT": 0.466,
      "FG3M": 12,
      "FG3A": 44,
      "FG3_PCT": 0.273,
      "FTM": 65,
      "FTA": 74,
      "FT_PCT": 0.878,
      "OREB": 18,
      "DREB": 64,
      "REB": 82,
      "AST": 25,
      "TOV": 22,
      "STL": 8,
      "BLK": 19,
      "BLKA": 3,
      "PF": 24,
      "PFD": 58,
      "PTS": 213,
      "PLUS_MINUS": 77,
      "NBA_FANTASY_PTS": 407.9,
      "DD2": 2,
      "TD3": 0,
      "GP_RANK": 1,
      "W_RANK": 1,
      "L_RANK": 1,
      "W_PCT_RANK": 1,
      "MIN_RANK": 1,
      "FGM_RANK": 1,
      "FGA_RANK": 1,
      "FG_PCT_RANK": 1,
      "FG3M_RANK": 1,
      "FG3A_RANK": 1,
      "FG3_PCT_RANK": 1,
      "FTM_RANK": 1,
      "FTA_RANK": 1,
      "FT_PCT_RANK": 1,
      "OREB_RANK": 1,
      "DREB_RANK": 1,
      "REB_RANK": 1,
      "AST_RANK": 1,
      "TOV_RANK": 1,
      "STL_RANK": 1,
      "BLK_RANK": 1,
      "BLKA_RANK": 1,
      "PF_RANK": 1,
      "PFD_RANK": 1,
      "PTS_RANK": 1,
      "PLUS_MINUS_RANK": 1,
      "NBA_FANTASY_PTS_RANK": 1,
      "DD2_RANK": 1,
      "TD3_RANK": 1,
      "CFID": 36,
      "CFPARAMS": "2021-22"
    },
    "Dwight Powell": {
      "id": 203939,
      "playing_state": "active",
      "GROUP_SET": "Last 10 Games",
      "GROUP_VALUE": "2021-22",
      "GP": 10,
      "W": 8,
      "L": 2,
      "W_PCT": 0.8,
      "MIN": 204.52833333333334,
      "FGM": 31,
      "FGA": 38,
      "FG_PCT": 0.816,
      "FG3M": 1,
      "FG3A": 2,
      "FG3_PCT": 0.5,
      "FTM": 26,
      "FTA": 33,
      "FT_PCT": 0.788,
      "OREB": 18,
      "DREB": 21,
      "REB": 39,
      "AST": 11,
      "TOV": 4,
      "STL": 3,
      "BLK": 2,
      "BLKA": 2,
      "PF": 18,
      "PFD": 31,
      "PTS": 89,
      "PLUS_MINUS": 49,
      "NBA_FANTASY_PTS": 163.3,
      "DD2": 0,
      "TD3": 0,
      "GP_RANK": 1,
      "W_RANK": 1,
      "L_RANK": 1,
      "W_PCT_RANK": 1,
      "MIN_RANK": 1,
      "FGM_RANK": 1,
      "FGA_RANK": 1,
      "FG_PCT_RANK": 1,
      "FG3M_RANK": 1,
      "FG3A_RANK": 1,
      "FG3_PCT_RANK": 1,
      "FTM_RANK": 1,
      "FTA_RANK": 1,
      "FT_PCT_RANK": 1,
      "OREB_RANK": 1,
      "DREB_RANK": 1,
      "REB_RANK": 1,
      "AST_RANK": 1,
      "TOV_RANK": 1,
      "STL_RANK": 1,
      "BLK_RANK": 1,
      "BLKA_RANK": 1,
      "PF_RANK": 1,
      "PFD_RANK": 1,
      "PTS_RANK": 1,
      "PLUS_MINUS_RANK": 1,
      "NBA_FANTASY_PTS_RANK": 1,
      "DD2_RANK": 1,
      "TD3_RANK": 1,
      "CFID": 36,
      "CFPARAMS": "2021-22"
    },
    "Josh Green": {
      "id": 1630182,
      "playing_state": "active",
      "GROUP_SET": "Last 10 Games",
      "GROUP_VALUE": "2021-22",
      "GP": 10,
      "W": 8,
      "L": 2,
      "W_PCT": 0.8,
      "MIN": 151.76833333333335,
      "FGM": 25,
      "FGA": 39,
      "FG_PCT": 0.641,
      "FG3M": 4,
      "FG3A": 8,
      "FG3_PCT": 0.5,
      "FTM": 6,
      "FTA": 10,
      "FT_PCT": 0.6,
      "OREB": 8,
      "DREB": 12,
      "REB": 20,
      "AST": 9,
      "TOV": 5,
      "STL": 5,
      "BLK": 0,
      "BLKA": 1,
      "PF": 24,
      "PFD": 9,
      "PTS": 60,
      "PLUS_MINUS": 13,
      "NBA_FANTASY_PTS": 107.5,
      "DD2": 0,
      "TD3": 0,
      "GP_RANK": 1,
      "W_RANK": 1,
      "L_RANK": 1,
      "W_PCT_RANK": 1,
      "MIN_RANK": 1,
      "FGM_RANK": 1,
      "FGA_RANK": 1,
      "FG_PCT_RANK": 1,
      "FG3M_RANK": 1,
      "FG3A_RANK": 1,
      "FG3_PCT_RANK": 1,
      "FTM_RANK": 1,
      "FTA_RANK": 1,
      "FT_PCT_RANK": 1,
      "OREB_RANK": 1,
      "DREB_RANK": 1,
      "REB_RANK": 1,
      "AST_RANK": 1,
      "TOV_RANK": 1,
      "STL_RANK": 1,
      "BLK_RANK": 1,
      "BLKA_RANK": 1,
      "PF_RANK": 1,
      "PFD_RANK": 1,
      "PTS_RANK": 1,
      "PLUS_MINUS_RANK": 1,
      "NBA_FANTASY_PTS_RANK": 1,
      "DD2_RANK": 1,
      "TD3_RANK": 1,
      "CFID": 36,
      "CFPARAMS": "2021-22"
    },
    "Moses Brown": {
      "id": 1629650,
      "playing_state": "active",
      "GROUP_SET": "Last 10 Games",
      "GROUP_VALUE": "2021-22",
      "GP": 10,
      "W": 6,
      "L": 4,
      "W_PCT": 0.6,
      "MIN": 67.18666666666667,
      "FGM": 12,
      "FGA": 24,
      "FG_PCT": 0.5,
      "FG3M": 0,
      "FG3A": 0,
      "FG3_PCT": 0.0,
      "FTM": 5,
      "FTA": 12,
      "FT_PCT": 0.417,
      "OREB": 5,
      "DREB": 23,
      "REB": 28,
      "AST": 0,
      "TOV": 8,
      "STL": 0,
      "BLK": 2,
      "BLKA": 3,
      "PF": 13,
      "PFD": 7,
      "PTS": 29,
      "PLUS_MINUS": -12,
      "NBA_FANTASY_PTS": 60.6,
      "DD2": 0,
      "TD3": 0,
      "GP_RANK": 1,
      "W_RANK": 1,
      "L_RANK": 1,
      "W_PCT_RANK": 1,
      "MIN_RANK": 1,
      "FGM_RANK": 1,
      "FGA_RANK": 1,
      "FG_PCT_RANK": 1,
      "FG3M_RANK": 1,
      "FG3A_RANK": 1,
      "FG3_PCT_RANK": 1,
      "FTM_RANK": 1,
      "FTA_RANK": 1,
      "FT_PCT_RANK": 1,
      "OREB_RANK": 1,
      "DREB_RANK": 1,
      "REB_RANK": 1,
      "AST_RANK": 1,
      "TOV_RANK": 1,
      "STL_RANK": 1,
      "BLK_RANK": 1,
      "BLKA_RANK": 1,
      "PF_RANK": 1,
      "PFD_RANK": 1,
      "PTS_RANK": 1,
      "PLUS_MINUS_RANK": 1,
      "NBA_FANTASY_PTS_RANK": 1,
      "DD2_RANK": 1,
      "TD3_RANK": 1,
      "CFID": 36,
      "CFPARAMS": "2021-22"
    },
    "Dorian Finney-Smith": {
      "id": 1627827,
      "playing_state": "active",
      "GROUP_SET": "Last 10 Games",
      "GROUP_VALUE": "2021-22",
      "GP": 10,
      "W": 8,
      "L": 2,
      "W_PCT": 0.8,
      "MIN": 299.48333333333335,
      "FGM": 39,
      "FGA": 86,
      "FG_PCT": 0.453,
      "FG3M": 18,
      "FG3A": 49,
      "FG3_PCT": 0.367,
      "FTM": 6,
      "FTA": 10,
      "FT_PCT": 0.6,
      "OREB": 12,
      "DREB": 36,
      "REB": 48,
      "AST": 14,
      "TOV": 12,
      "STL": 7,
      "BLK": 5,
      "BLKA": 5,
      "PF": 19,
      "PFD": 7,
      "PTS": 102,
      "PLUS_MINUS": 39,
      "NBA_FANTASY_PTS": 204.6,
      "DD2": 1,
      "TD3": 0,
      "GP_RANK": 1,
      "W_RANK": 1,
      "L_RANK": 1,
      "W_PCT_RANK": 1,
      "MIN_RANK": 1,
      "FGM_RANK": 1,
      "FGA_RANK": 1,
      "FG_PCT_RANK": 1,
      "FG3M_RANK": 1,
      "FG3A_RANK": 1,
      "FG3_PCT_RANK": 1,
      "FTM_RANK": 1,
      "FTA_RANK": 1,
      "FT_PCT_RANK": 1,
      "OREB_RANK": 1,
      "DREB_RANK": 1,
      "REB_RANK": 1,
      "AST_RANK": 1,
      "TOV_RANK": 1,
      "STL_RANK": 1,
      "BLK_RANK": 1,
      "BLKA_RANK": 1,
      "PF_RANK": 1,
      "PFD_RANK": 1,
      "PTS_RANK": 1,
      "PLUS_MINUS_RANK": 1,
      "NBA_FANTASY_PTS_RANK": 1,
      "DD2_RANK": 1,
      "TD3_RANK": 1,
      "CFID": 36,
      "CFPARAMS": "2021-22"
    },
    "Tim Hardaway Jr.": {
      "id": 203501,
      "playing_state": "active",
      "GROUP_SET": "Last 10 Games",
      "GROUP_VALUE": "2021-22",
      "GP": 10,
      "W": 8,
      "L": 2,
      "W_PCT": 0.8,
      "MIN": 265.85,
      "FGM": 46,
      "FGA": 115,
      "FG_PCT": 0.4,
      "FG3M": 24,
      "FG3A": 69,
      "FG3_PCT": 0.348,
      "FTM": 17,
      "FTA": 23,
      "FT_PCT": 0.739,
      "OREB": 1,
      "DREB": 32,
      "REB": 33,
      "AST": 18,
      "TOV": 10,
      "STL": 9,
      "BLK": 2,
      "BLKA": 1,
      "PF": 16,
      "PFD": 21,
      "PTS": 133,
      "PLUS_MINUS": 43,
      "NBA_FANTASY_PTS": 222.6,
      "DD2": 0,
      "TD3": 0,
      "GP_RANK": 1,
      "W_RANK": 1,
      "L_RANK": 1,
      "W_PCT_RANK": 1,
      "MIN_RANK": 1,
      "FGM_RANK": 1,
      "FGA_RANK": 1,
      "FG_PCT_RANK": 1,
      "FG3M_RANK": 1,
      "FG3A_RANK": 1,
      "FG3_PCT_RANK": 1,
      "FTM_RANK": 1,
      "FTA_RANK": 1,
      "FT_PCT_RANK": 1,
      "OREB_RANK": 1,
      "DREB_RANK": 1,
      "REB_RANK": 1,
      "AST_RANK": 1,
      "TOV_RANK": 1,
      "STL_RANK": 1,
      "BLK_RANK": 1,
      "BLKA_RANK": 1,
      "PF_RANK": 1,
      "PFD_RANK": 1,
      "PTS_RANK": 1,
      "PLUS_MINUS_RANK": 1,
      "NBA_FANTASY_PTS_RANK": 1,
      "DD2_RANK": 1,
      "TD3_RANK": 1,
      "CFID": 36,
      "CFPARAMS": "2021-22"
    },
    "Jalen Brunson": {
      "id": 1628973,
      "playing_state": "active",
      "GROUP_SET": "Last 10 Games",
      "GROUP_VALUE": "2021-22",
      "GP": 10,
      "W": 8,
      "L": 2,
      "W_PCT": 0.8,
      "MIN": 324.135,
      "FGM": 63,
      "FGA": 123,
      "FG_PCT": 0.512,
      "FG3M": 6,
      "FG3A": 21,
      "FG3_PCT": 0.286,
      "FTM": 17,
      "FTA": 19,
      "FT_PCT": 0.895,
      "OREB": 5,
      "DREB": 38,
      "REB": 43,
      "AST": 53,
      "TOV": 19,
      "STL": 14,
      "BLK": 0,
      "BLKA": 4,
      "PF": 17,
      "PFD": 27,
      "PTS": 149,
      "PLUS_MINUS": 47,
      "NBA_FANTASY_PTS": 303.1,
      "DD2": 1,
      "TD3": 0,
      "GP_RANK": 1,
      "W_RANK": 1,
      "L_RANK": 1,
      "W_PCT_RANK": 1,
      "MIN_RANK": 1,
      "FGM_RANK": 1,
      "FGA_RANK": 1,
      "FG_PCT_RANK": 1,
      "FG3M_RANK": 1,
      "FG3A_RANK": 1,
      "FG3_PCT_RANK": 1,
      "FTM_RANK": 1,
      "FTA_RANK": 1,
      "FT_PCT_RANK": 1,
      "OREB_RANK": 1,
      "DREB_RANK": 1,
      "REB_RANK": 1,
      "AST_RANK": 1,
      "TOV_RANK": 1,
      "STL_RANK": 1,
      "BLK_RANK": 1,
      "BLKA_RANK": 1,
      "PF_RANK": 1,
      "PFD_RANK": 1,
      "PTS_RANK": 1,
      "PLUS_MINUS_RANK": 1,
      "NBA_FANTASY_PTS_RANK": 1,
      "DD2_RANK": 1,
      "TD3_RANK": 1,
      "CFID": 36,
      "CFPARAMS": "2021-22"
    },
    "Frank Ntilikina": {
      "id": 1628373,
      "playing_state": "active",
      "GROUP_SET": "Last 10 Games",
      "GROUP_VALUE": "2021-22",
      "GP": 10,
      "W": 8,
      "L": 2,
      "W_PCT": 0.8,
      "MIN": 44.166666666666664,
      "FGM": 7,
      "FGA": 16,
      "FG_PCT": 0.438,
      "FG3M": 4,
      "FG3A": 8,
      "FG3_PCT": 0.5,
      "FTM": 0,
      "FTA": 0,
      "FT_PCT": 0.0,
      "OREB": 2,
      "DREB": 6,
      "REB": 8,
      "AST": 7,
      "TOV": 4,
      "STL": 2,
      "BLK": 0,
      "BLKA": 0,
      "PF": 5,
      "PFD": 0,
      "PTS": 18,
      "PLUS_MINUS": 3,
      "NBA_FANTASY_PTS": 40.1,
      "DD2": 0,
      "TD3": 0,
      "GP_RANK": 1,
      "W_RANK": 1,
      "L_RANK": 1,
      "W_PCT_RANK": 1,
      "MIN_RANK": 1,
      "FGM_RANK": 1,
      "FGA_RANK": 1,
      "FG_PCT_RANK": 1,
      "FG3M_RANK": 1,
      "FG3A_RANK": 1,
      "FG3_PCT_RANK": 1,
      "FTM_RANK": 1,
      "FTA_RANK": 1,
      "FT_PCT_RANK": 1,
      "OREB_RANK": 1,
      "DREB_RANK": 1,
      "REB_RANK": 1,
      "AST_RANK": 1,
      "TOV_RANK": 1,
      "STL_RANK": 1,
      "BLK_RANK": 1,
      "BLKA_RANK": 1,
      "PF_RANK": 1,
      "PFD_RANK": 1,
      "PTS_RANK": 1,
      "PLUS_MINUS_RANK": 1,
      "NBA_FANTASY_PTS_RANK": 1,
      "DD2_RANK": 1,
      "TD3_RANK": 1,
      "CFID": 36,
      "CFPARAMS": "2021-22"
    },
    "Theo Pinson": {
      "id": 1629033,
      "playing_state": "active",
      "GROUP_SET": "Last 10 Games",
      "GROUP_VALUE": "2021-22",
      "GP": 10,
      "W": 6,
      "L": 4,
      "W_PCT": 0.6,
      "MIN": 72.68,
      "FGM": 6,
      "FGA": 20,
      "FG_PCT": 0.3,
      "FG3M": 4,
      "FG3A": 16,
      "FG3_PCT": 0.25,
      "FTM": 2,
      "FTA": 2,
      "FT_PCT": 1.0,
      "OREB": 0,
      "DREB": 12,
      "REB": 12,
      "AST": 9,
      "TOV": 1,
      "STL": 0,
      "BLK": 1,
      "BLKA": 0,
      "PF": 8,
      "PFD": 2,
      "PTS": 18,
      "PLUS_MINUS": -22,
      "NBA_FANTASY_PTS": 47.9,
      "DD2": 0,
      "TD3": 0,
      "GP_RANK": 1,
      "W_RANK": 1,
      "L_RANK": 1,
      "W_PCT_RANK": 1,
      "MIN_RANK": 1,
      "FGM_RANK": 1,
      "FGA_RANK": 1,
      "FG_PCT_RANK": 1,
      "FG3M_RANK": 1,
      "FG3A_RANK": 1,
      "FG3_PCT_RANK": 1,
      "FTM_RANK": 1,
      "FTA_RANK": 1,
      "FT_PCT_RANK": 1,
      "OREB_RANK": 1,
      "DREB_RANK": 1,
      "REB_RANK": 1,
      "AST_RANK": 1,
      "TOV_RANK": 1,
      "STL_RANK": 1,
      "BLK_RANK": 1,
      "BLKA_RANK": 1,
      "PF_RANK": 1,
      "PFD_RANK": 1,
      "PTS_RANK": 1,
      "PLUS_MINUS_RANK": 1,
      "NBA_FANTASY_PTS_RANK": 1,
      "DD2_RANK": 1,
      "TD3_RANK": 1,
      "CFID": 36,
      "CFPARAMS": "2021-22"
    },
    "Reggie Bullock": {
      "id": 203493,
      "playing_state": "active",
      "GROUP_SET": "Last 10 Games",
      "GROUP_VALUE": "2021-22",
      "GP": 10,
      "W": 8,
      "L": 2,
      "W_PCT": 0.8,
      "MIN": 221.19666666666666,
      "FGM": 24,
      "FGA": 58,
      "FG_PCT": 0.414,
      "FG3M": 19,
      "FG3A": 47,
      "FG3_PCT": 0.404,
      "FTM": 3,
      "FTA": 4,
      "FT_PCT": 0.75,
      "OREB": 10,
      "DREB": 31,
      "REB": 41,
      "AST": 18,
      "TOV": 2,
      "STL": 5,
      "BLK": 2,
      "BLKA": 1,
      "PF": 9,
      "PFD": 3,
      "PTS": 70,
      "PLUS_MINUS": 113,
      "NBA_FANTASY_PTS": 165.2,
      "DD2": 0,
      "TD3": 0,
      "GP_RANK": 1,
      "W_RANK": 1,
      "L_RANK": 1,
      "W_PCT_RANK": 1,
      "MIN_RANK": 1,
      "FGM_RANK": 1,
      "FGA_RANK": 1,
      "FG_PCT_RANK": 1,
      "FG3M_RANK": 1,
      "FG3A_RANK": 1,
      "FG3_PCT_RANK": 1,
      "FTM_RANK": 1,
      "FTA_RANK": 1,
      "FT_PCT_RANK": 1,
      "OREB_RANK": 1,
      "DREB_RANK": 1,
      "REB_RANK": 1,
      "AST_RANK": 1,
      "TOV_RANK": 1,
      "STL_RANK": 1,
      "BLK_RANK": 1,
      "BLKA_RANK": 1,
      "PF_RANK": 1,
      "PFD_RANK": 1,
      "PTS_RANK": 1,
      "PLUS_MINUS_RANK": 1,
      "NBA_FANTASY_PTS_RANK": 1,
      "DD2_RANK": 1,
      "TD3_RANK": 1,
      "CFID": 36,
      "CFPARAMS": "2021-22"
    },
    "Maxi Kleber": {
      "id": 1628467,
      "playing_state": "active",
      "GROUP_SET": "Last 10 Games",
      "GROUP_VALUE": "2021-22",
      "GP": 10,
      "W": 8,
      "L": 2,
      "W_PCT": 0.8,
      "MIN": 271.19666666666666,
      "FGM": 24,
      "FGA": 67,
      "FG_PCT": 0.358,
      "FG3M": 18,
      "FG3A": 53,
      "FG3_PCT": 0.34,
      "FTM": 4,
      "FTA": 5,
      "FT_PCT": 0.8,
      "OREB": 9,
      "DREB": 47,
      "REB": 56,
      "AST": 15,
      "TOV": 11,
      "STL": 4,
      "BLK": 9,
      "BLKA": 5,
      "PF": 25,
      "PFD": 16,
      "PTS": 70,
      "PLUS_MINUS": 58,
      "NBA_FANTASY_PTS": 187.7,
      "DD2": 0,
      "TD3": 0,
      "GP_RANK": 1,
      "W_RANK": 1,
      "L_RANK": 1,
      "W_PCT_RANK": 1,
      "MIN_RANK": 1,
      "FGM_RANK": 1,
      "FGA_RANK": 1,
      "FG_PCT_RANK": 1,
      "FG3M_RANK": 1,
      "FG3A_RANK": 1,
      "FG3_PCT_RANK": 1,
      "FTM_RANK": 1,
      "FTA_RANK": 1,
      "FT_PCT_RANK": 1,
      "OREB_RANK": 1,
      "DREB_RANK": 1,
      "REB_RANK": 1,
      "AST_RANK": 1,
      "TOV_RANK": 1,
      "STL_RANK": 1,
      "BLK_RANK": 1,
      "BLKA_RANK": 1,
      "PF_RANK": 1,
      "PFD_RANK": 1,
      "PTS_RANK": 1,
      "PLUS_MINUS_RANK": 1,
      "NBA_FANTASY_PTS_RANK": 1,
      "DD2_RANK": 1,
      "TD3_RANK": 1,
      "CFID": 36,
      "CFPARAMS": "2021-22"
    },
    "Boban Marjanovic": {
      "id": 1626246,
      "playing_state": "active",
      "GROUP_SET": "Last 10 Games",
      "GROUP_VALUE": "2021-22",
      "GP": 10,
      "W": 6,
      "L": 4,
      "W_PCT": 0.6,
      "MIN": 56.391666666666666,
      "FGM": 20,
      "FGA": 34,
      "FG_PCT": 0.588,
      "FG3M": 1,
      "FG3A": 3,
      "FG3_PCT": 0.333,
      "FTM": 5,
      "FTA": 8,
      "FT_PCT": 0.625,
      "OREB": 2,
      "DREB": 17,
      "REB": 19,
      "AST": 0,
      "TOV": 6,
      "STL": 0,
      "BLK": 1,
      "BLKA": 3,
      "PF": 10,
      "PFD": 9,
      "PTS": 46,
      "PLUS_MINUS": 19,
      "NBA_FANTASY_PTS": 65.8,
      "DD2": 0,
      "TD3": 0,
      "GP_RANK": 1,
      "W_RANK": 1,
      "L_RANK": 1,
      "W_PCT_RANK": 1,
      "MIN_RANK": 1,
      "FGM_RANK": 1,
      "FGA_RANK": 1,
      "FG_PCT_RANK": 1,
      "FG3M_RANK": 1,
      "FG3A_RANK": 1,
      "FG3_PCT_RANK": 1,
      "FTM_RANK": 1,
      "FTA_RANK": 1,
      "FT_PCT_RANK": 1,
      "OREB_RANK": 1,
      "DREB_RANK": 1,
      "REB_RANK": 1,
      "AST_RANK": 1,
      "TOV_RANK": 1,
      "STL_RANK": 1,
      "BLK_RANK": 1,
      "BLKA_RANK": 1,
      "PF_RANK": 1,
      "PFD_RANK": 1,
      "PTS_RANK": 1,
      "PLUS_MINUS_RANK": 1,
      "NBA_FANTASY_PTS_RANK": 1,
      "DD2_RANK": 1,
      "TD3_RANK": 1,
      "CFID": 36,
      "CFPARAMS": "2021-22"
    },
    "Luka Doncic": {
      "id": 1629029,
      "playing_state": "active",
      "GROUP_SET": "Last 10 Games",
      "GROUP_VALUE": "2021-22",
      "GP": 10,
      "W": 8,
      "L": 2,
      "W_PCT": 0.8,
      "MIN": 353.5133333333333,
      "FGM": 81,
      "FGA": 201,
      "FG_PCT": 0.403,
      "FG3M": 15,
      "FG3A": 72,
      "FG3_PCT": 0.208,
      "FTM": 66,
      "FTA": 80,
      "FT_PCT": 0.825,
      "OREB": 8,
      "DREB": 96,
      "REB": 104,
      "AST": 92,
      "TOV": 47,
      "STL": 14,
      "BLK": 3,
      "BLKA": 4,
      "PF": 20,
      "PFD": 70,
      "PTS": 243,
      "PLUS_MINUS": 69,
      "NBA_FANTASY_PTS": 509.8,
      "DD2": 7,
      "TD3": 3,
      "GP_RANK": 1,
      "W_RANK": 1,
      "L_RANK": 1,
      "W_PCT_RANK": 1,
      "MIN_RANK": 1,
      "FGM_RANK": 1,
      "FGA_RANK": 1,
      "FG_PCT_RANK": 1,
      "FG3M_RANK": 1,
      "FG3A_RANK": 1,
      "FG3_PCT_RANK": 1,
      "FTM_RANK": 1,
      "FTA_RANK": 1,
      "FT_PCT_RANK": 1,
      "OREB_RANK": 1,
      "DREB_RANK": 1,
      "REB_RANK": 1,
      "AST_RANK": 1,
      "TOV_RANK": 1,
      "STL_RANK": 1,
      "BLK_RANK": 1,
      "BLKA_RANK": 1,
      "PF_RANK": 1,
      "PFD_RANK": 1,
      "PTS_RANK": 1,
      "PLUS_MINUS_RANK": 1,
      "NBA_FANTASY_PTS_RANK": 1,
      "DD2_RANK": 1,
      "TD3_RANK": 1,
      "CFID": 36,
      "CFPARAMS": "2021-22"
    }
  },
  "date": "1.21.2022"
}